[
  {
    "description": "   Test the login function",
    "elements": [
      {
        "id": "example-about-login-function;verify-that-user-can-login",
        "keyword": "Scenario",
        "line": 7,
        "name": "Verify that user can login",
        "steps": [
          {
            "arguments": [],
            "keyword": "Given ",
            "name": "I login the app with username \"automationtestervietnam@gmail.com\" and pass \"chimpdemo123456\"",
            "result": {
              "status": "failed",
              "duration": 15834488756,
              "error_message": "Error: Element is not currently visible and may not be manipulated\n    at Object.wait (C:\\Users\\padung\\AppData\\Roaming\\npm\\node_modules\\chimp\\node_modules\\fibers\\future.js:449:15)\n    at Object.click (C:\\Users\\padung\\AppData\\Roaming\\npm\\node_modules\\chimp\\node_modules\\wdio-sync\\build\\index.js:344:27)\n    at World.<anonymous> (C:/Users/padung/Desktop/chimp_project/features/step_definitions/loginPageSteps.js:8:31)\n    at C:\\Users\\padung\\AppData\\Roaming\\npm\\node_modules\\chimp\\node_modules\\meteor-promise\\fiber_pool.js:43:40"
            },
            "line": 5,
            "match": {
              "location": "C:/Users/padung/Desktop/chimp_project/features/step_definitions/loginPageSteps.js:6"
            }
          },
          {
            "arguments": [],
            "keyword": "Then ",
            "name": "I see the user icon with name \"AUTOMATION TESTERVIETNAM\"",
            "result": {
              "status": "skipped"
            },
            "line": 8,
            "match": {
              "location": "C:/Users/padung/Desktop/chimp_project/features/step_definitions/mainPageSteps.js:11"
            }
          },
          {
            "arguments": [],
            "keyword": "When ",
            "name": "I click on the user icon",
            "result": {
              "status": "skipped"
            },
            "line": 9,
            "match": {
              "location": "C:/Users/padung/Desktop/chimp_project/features/step_definitions/mainPageSteps.js:7"
            }
          },
          {
            "arguments": [],
            "keyword": "And ",
            "name": "I select the option \"My Profile\"",
            "result": {
              "status": "skipped"
            },
            "line": 10,
            "match": {
              "location": "C:/Users/padung/Desktop/chimp_project/features/step_definitions/mainPageSteps.js:15"
            }
          },
          {
            "arguments": [],
            "keyword": "Then ",
            "name": "I see the page \"My Profile1\" displayed",
            "result": {
              "status": "skipped"
            },
            "line": 11,
            "match": {
              "location": "C:/Users/padung/Desktop/chimp_project/features/step_definitions/mainPageSteps.js:19"
            }
          },
          {
            "arguments": [],
            "keyword": "After ",
            "result": {
              "status": "passed",
              "duration": 255359
            },
            "hidden": true,
            "match": {
              "location": "C:\\Users\\padung\\AppData\\Roaming\\npm\\node_modules\\chimp\\dist\\lib\\cucumberjs\\hooks.js:68"
            }
          }
        ],
        "tags": [
          {
            "name": "@watch",
            "line": 6
          }
        ],
        "type": "scenario"
      },
      {
        "id": "example-about-login-function;verify-that-user-can-login-2",
        "keyword": "Scenario",
        "line": 14,
        "name": "Verify that user can login 2",
        "steps": [
          {
            "arguments": [],
            "keyword": "Given ",
            "name": "I login the app with username \"automationtestervietnam@gmail.com\" and pass \"chimpdemo123456\"",
            "result": {
              "status": "failed",
              "duration": 5349934749,
              "error_message": "Error: Element is not currently visible and may not be manipulated\n    at Object.wait (C:\\Users\\padung\\AppData\\Roaming\\npm\\node_modules\\chimp\\node_modules\\fibers\\future.js:449:15)\n    at Object.click (C:\\Users\\padung\\AppData\\Roaming\\npm\\node_modules\\chimp\\node_modules\\wdio-sync\\build\\index.js:344:27)\n    at World.<anonymous> (C:/Users/padung/Desktop/chimp_project/features/step_definitions/loginPageSteps.js:8:31)\n    at C:\\Users\\padung\\AppData\\Roaming\\npm\\node_modules\\chimp\\node_modules\\meteor-promise\\fiber_pool.js:43:40"
            },
            "line": 5,
            "match": {
              "location": "C:/Users/padung/Desktop/chimp_project/features/step_definitions/loginPageSteps.js:6"
            }
          },
          {
            "arguments": [],
            "keyword": "Then ",
            "name": "I see the user icon with name \"AUTOMATION TESTERVIETNAM\"",
            "result": {
              "status": "skipped"
            },
            "line": 15,
            "match": {
              "location": "C:/Users/padung/Desktop/chimp_project/features/step_definitions/mainPageSteps.js:11"
            }
          },
          {
            "arguments": [],
            "keyword": "When ",
            "name": "I click on the user icon",
            "result": {
              "status": "skipped"
            },
            "line": 16,
            "match": {
              "location": "C:/Users/padung/Desktop/chimp_project/features/step_definitions/mainPageSteps.js:7"
            }
          },
          {
            "arguments": [],
            "keyword": "And ",
            "name": "I select the option \"My Profile123456\"",
            "result": {
              "status": "skipped"
            },
            "line": 17,
            "match": {
              "location": "C:/Users/padung/Desktop/chimp_project/features/step_definitions/mainPageSteps.js:15"
            }
          },
          {
            "arguments": [],
            "keyword": "After ",
            "result": {
              "status": "passed",
              "duration": 114206
            },
            "hidden": true,
            "match": {
              "location": "C:\\Users\\padung\\AppData\\Roaming\\npm\\node_modules\\chimp\\dist\\lib\\cucumberjs\\hooks.js:68"
            }
          }
        ],
        "tags": [
          {
            "name": "@watch",
            "line": 13
          }
        ],
        "type": "scenario"
      }
    ],
    "id": "example-about-login-function",
    "keyword": "Feature",
    "line": 1,
    "name": "Example about login function",
    "tags": [],
    "uri": "C:/Users/padung/Desktop/chimp_project/features/login.feature"
  }
]